sam2/__init__.py
sam2/automatic_mask_generator.py
sam2/build_sam.py
sam2/sam2_camera_predictor.py
sam2/sam2_image_predictor.py
sam2/sam2_video_predictor.py
sam2/configs/__init__.py
sam2/configs/sam2.1_hiera_t.yaml
sam2/configs/sam2_hiera_b+.yaml
sam2/configs/sam2_hiera_l.yaml
sam2/configs/sam2_hiera_s.yaml
sam2/configs/sam2_hiera_t.yaml
sam2/modeling/__init__.py
sam2/modeling/memory_attention.py
sam2/modeling/memory_encoder.py
sam2/modeling/position_encoding.py
sam2/modeling/sam2_base.py
sam2/modeling/sam2_utils.py
sam2/modeling/backbones/__init__.py
sam2/modeling/backbones/hieradet.py
sam2/modeling/backbones/image_encoder.py
sam2/modeling/backbones/utils.py
sam2/modeling/sam/__init__.py
sam2/modeling/sam/mask_decoder.py
sam2/modeling/sam/prompt_encoder.py
sam2/modeling/sam/transformer.py
sam2/utils/__init__.py
sam2/utils/amg.py
sam2/utils/download.py
sam2/utils/misc.py
sam2/utils/transforms.py
sam2/utils/visualization.py
samv2_webcam-0.0.3.dist-info/WHEEL
samv2_webcam-0.0.3.dist-info/METADATA
samv2_webcam-0.0.3.dist-info/RECORD
