Metadata-Version: 2.3
Name: samv2_webcam
Version: 0.0.3
Summary: CPU compatible fork of the official SAMv2 implementation with Webcam support
Keywords: deep-learning,pytorch
Author-email: Sonny Kurniawan <sonny.kurniawan.yap@gmail.com>
Requires-Python: >=3.8
Requires-Dist: torch>=2.3.1
Requires-Dist: torchvision>=0.18.1
Requires-Dist: numpy>=1.24.4
Requires-Dist: tqdm>=4.66.1
Requires-Dist: hydra-core>=1.3.2
Requires-Dist: iopath>=0.1.10
Requires-Dist: pillow>=9.4.0
Requires-Dist: samv2[test, dev] ; extra == "all"
Requires-Dist: black ; extra == "dev"
Requires-Dist: isort ; extra == "dev"
Requires-Dist: pre-commit>=2.18.0 ; extra == "dev"
Requires-Dist: pytest ; extra == "test"
Project-URL: homepage, https://github.com/sonnyky/samv2
Project-URL: repository, https://github.com/sonnyky/samv2
Provides-Extra: all
Provides-Extra: dev
Provides-Extra: test
